{
    "displayName":"手势贴纸",
    "displayNameEn":"Gesture Stickers",
    "downloadPath":"MotionRes/handMotionRes/",
    "propertyList":[
        {
            "displayName":"无",
            "displayNameEn":"None",
            "icon":"beauty_panel/panel_icon/beauty/none.png"
        },
        {
            "displayName":"樱花女孩",
            "displayNameEn":"Sakura",
            "resourceUri":"MotionRes/handMotionRes/video_sakuragirl",
            "icon":"beauty_panel/panel_icon/motions_icon/video_sakuragirl.png"
        }
    ]
}